{
  "system": "نظام الرقابة المالية",
  "category": "financial_control",
  "questions": [
    {
      "q": "ما هو نظام الرقابة المالية في السعودية؟",
      "a": "نظام الرقابة المالية: يراقب المال العام ويضمن الاستخدام السليم. الجهة المنفذة: الهيئة العامة للرقابة المالية تحت مجلس الوزراء. تدقيق الجهات الحكومية والشركات المملوكة للدولة.",
      "keywords": [
        "رقابة مالية",
        "هيئة رقابة",
        "تدقيق مالي",
        "مال عام",
        "حسابات حكومية"
      ]
    },
    {
      "q": "ما هي صلاحيات الهيئة العامة للرقابة المالية؟",
      "a": "الصلاحيات: 1) تدقيق حسابات الجهات الحكومية، 2) فحص الوثائق المالية، 3) طلب المعلومات من المسؤولين، 4) اكتشاف المخالفات المالية، 5) رفع التقارير لمجلس الوزراء.",
      "keywords": [
        "صلاحيات رقابة",
        "تدقيق",
        "فحص مالي",
        "مخالفات مالية"
      ]
    },
    {
      "q": "ما هي عقوبات المخالفات المالية في القطاع العام؟",
      "a": "المخالفات: 1) التأديب الوظيفي للمخالفين، 2) المساءلة المالية رد المبالغ المسروقة، 3) السجن حتى 10 سنوات للاختلاس، 4) الغرامات المالية، 5) الفصل من الخدمة.",
      "keywords": [
        "عقوبات مالية",
        "اختلاس",
        "سرقة مال عام",
        "فساد مالي"
      ]
    }
  ]
}