{
  "system": "نظام الحج والعمرة",
  "category": "hajj_umrah",
  "questions": [
    {
      "q": "ما هو نظام الحج والعمرة في السعودية؟",
      "a": "نظام الحج والعمرة: ينظم شؤون الحجاج والمعتمرين والزوار. الهيئة المنفذة: وزارة الحج والعمرة. يشمل: التراخيص، النقل، الإسكان، الخدمات، نظام نسك.",
      "keywords": [
        "حج",
        "عمرة",
        "حاج",
        "معتمر",
        "وزارة حج",
        "نسك"
      ]
    },
    {
      "q": "ما هي حقوق الحاج والمعتمر في السعودية؟",
      "a": "حقوق الحاج: 1) خدمات النقل والإسكان المتفق عليها، 2) الرعاية الصحية، 3) الأمن والسلامة، 4) الإفادة من التسهيلات الحكومية، 5) الشكاوى لـ 911 أو وزارة الحج.",
      "keywords": [
        "حقوق حاج",
        "خدمات حج",
        "إسكان حجاج",
        "نقل حجاج"
      ]
    },
    {
      "q": "ما هي عقوبات الغش في خدمات الحج؟",
      "a": "الغش في خدمات الحج: غرامة تصل 50000 ريال والسجن حتى سنة. تشمل: الإخلال بالإسكان المتفق عليه، عدم توفير النقل، التلاعب في التأشيرات.",
      "keywords": [
        "غش حج",
        "عقوبات حج",
        "مخالفات حج",
        "نصب حجاج"
      ]
    }
  ]
}