{
  "system": "نظام المياه",
  "category": "water",
  "questions": [
    {
      "q": "ما هو نظام المياه في السعودية؟",
      "a": "نظام المياه: ينظم استخدام الموارد المائية وإدارتها. الهيئة المنفذة: وزارة البيئة والمياه والزراعة. يشمل: المياه الجوفية، مياه التحلية، إعادة الاستخدام.",
      "keywords": [
        "مياه",
        "نظام مياه",
        "موارد مائية",
        "تحلية مياه"
      ]
    },
    {
      "q": "ما هي حقوق استخدام المياه الجوفية؟",
      "a": "حقوق المياه الجوفية: يجب الحصول على ترخيص حفر بئر. تراخيص الاستغلال تُمنح للمشاريع الزراعية والصناعية. يُمنع حفر الآبار بدون ترخيص (غرامات مشددة).",
      "keywords": [
        "مياه جوفية",
        "بئر ماء",
        "ترخيص حفر",
        "حقوق مياه"
      ]
    },
    {
      "q": "ما هي عقوبات إهدار المياه؟",
      "a": "عقوبات إهدار المياه: غرامة 1,000-5,000 ريال للأفراد. للمنشآت: غرامة تصل 100,000 ريال. قد يصل الأمر إلى قطع الخدمة للمخالفين المتكررين.",
      "keywords": [
        "إهدار مياه",
        "غرامة مياه",
        "مخالفة مياه"
      ]
    }
  ]
}